{
  "id": "component/readme-subgraph",
  "title": "README Subgraph",
  "description": "This page explains the details of the README Subgraph.",
  "source": "@site/docs/component/readme-subgraph.md",
  "sourceDirName": "component",
  "slug": "/component/readme-subgraph",
  "permalink": "/airas/docs/component/readme-subgraph",
  "draft": false,
  "unlisted": false,
  "editUrl": "https://github.com/auto-res/airas/tree/main/docs/docs/component/readme-subgraph.md",
  "tags": [],
  "version": "current",
  "sidebarPosition": 8,
  "frontMatter": {
    "sidebar_position": 8
  },
  "sidebar": "tutorialSidebar",
  "previous": {
    "title": "LaTeX Subgraph",
    "permalink": "/airas/docs/component/latex-subgraph"
  },
  "next": {
    "title": "Research Preparation Subgraph",
    "permalink": "/airas/docs/component/research-preparation-subgraph"
  }
}